Workbook

Sheet Lisez-moi
A1: Analyse de risques ISO 14971 simplifiée — TP M3-2
A2: Module 3 — vendredi 16 octobre 2026 — MBA Santé, IA & IoT — Epitech — Nicolas LAURIO
A3: Exercice d'entraînement. Matrice d'exemple, simplifiée pour le cours : dans un vrai dossier, le fabricant définit lui-même ses échelles et ses seuils.
A5: Légende des cellules
A6: Police bleue sur fond bleu pâle = à remplir par l'équipe (listes déroulantes : type de danger, gravité, probabilité).
A7: Police noire sur fond blanc dans les colonnes « Risque » et « Niveau » = formule : ne pas écraser.
A8: Couleur automatique du niveau : vert pâle = faible (acceptable), orange clair = moyen (à réduire), orange foncé = élevé (inacceptable).
A10: La chaîne à remplir, de gauche à droite (comme une rangée de dominos)
A11: Danger (ce qui peut faire du mal) → séquence d'événements (ce qui s'enchaîne) → situation dangereuse (une personne est exposée) → dommage (l'atteinte à la santé).
A12: Puis : gravité (1 à 3) × probabilité (1 à 3) = risque → niveau. Puis 3 mesures, dans l'ordre imposé : 1) conception, 2) protection, 3) information. Puis on recote : c'est le risque résiduel.
A14: Onglets
A15: Échelles : définitions de la gravité et de la probabilité, seuils des zones, matrice 3 × 3.
... A20: Enregistrez sous analyse_risques_eqNN.xlsx (NN = numéro d'équipe) dans analyses/m3/ du dépôt. Au moins 5 dangers : techniques, d'utilisation, de cybersécurité.

Sheet Échelles
A1: Échelles de cotation (matrice d'exemple, simplifiée pour le cours)
A3: Gravité | B3: Nom | C3: Ce que ça veut dire (exemple : cas A, EHPAD)
A4: 1 | B4: Légère | C4: Gêne passagère, sans soins (ex. rougeur, résidente réveillée la nuit)
A5: 2 | B5: Modérée | C5: Soins nécessaires, puis guérison (ex. plaie à panser, hématome)
A6: 3 | B6: Grave | C6: Séquelles ou décès (ex. plusieurs heures au sol : déshydratation, escarres, hospitalisation)
A7: Probabilité | B7: Nom | C7: Ce que ça veut dire (repère pour un EHPAD équipé)
A8: 1 | B8: Rare | C8: On l'imagine difficilement : peut-être une fois en plusieurs années
A9: 2 | B9: Possible | C9: Cela arrivera sans doute un jour : quelques fois par an
A10: 3 | B10: Fréquente | C10: On s'y attend : chaque mois, voire plus souvent
A12: Seuils des zones (risque = gravité × probabilité, de 1 à 9)
A13: Zone | B13: Mot des slides | C13: À partir d'un risque de…
A14: À réduire | B14: Moyen | C14: 3 | D14: Moyen : réduire autant que possible, puis justifier par le bénéfice.
A15: Inacceptable | B15: Élevé | C15: 6 | D15: Élevé : inacceptable en l'état, il faut réduire le risque.
A16: Acceptable | B16: Faible | C16: en dessous de 3 (1 ou 2) | D16: Faible : acceptable, on le note quand même.
A18: Quelles cases dans quelle zone ?
A19: Faible (acceptable) : Légère × Rare (1), Légère × Possible (2), Modérée × Rare (2).
A20: Moyen (à réduire) : Légère × Fréquente (3), Grave × Rare (3), Modérée × Possible (4).
A21: Élevé (inacceptable) : Modérée × Fréquente (6), Grave × Possible (6), Grave × Fréquente (9).
A22: Conséquence : un dommage grave ne descend jamais sous « moyen ». On le réduit autant que possible, puis on justifie par le bénéfice pour le patient.
A24: Matrice 3 × 3 (calculée)
A25: Gravité ↓ / Probabilité → | B25: 1 Rare | C25: 2 Possible | D25: 3 Fréquente
A26: 3 Grave | B26: =VALUE(LEFT($A26,1))*VALUE(LEFT(B$25,1))&" : "&IF(VALUE(LEFT($A26,1))*VALUE(LEFT(B$25,1))>=$C$15,"Élevé",IF(VALUE(LEFT($A26,1))*VALUE(LEFT(B$25,1))>=$C$14,"Moyen","Faible")) | C26: =VALUE(LEFT($A26,1))*VALUE(LEFT(C$25,1))&" : "&IF(VALUE(LEFT($A26,1))*VALUE(LEFT(C$25,1))>=$C$15,"Élevé",IF(VALUE(LEFT($A26,1))*VALUE(LEFT(C$25,1))>=$C$14,"Moyen","Faible")) | D26: =VALUE(LEFT($A26,1))*VALUE(LEFT(D$25,1))&" : "&IF(VALUE(LEFT($A26,1))*VALUE(LEFT(D$25,1))>=$C$15,"Élevé",IF(VALUE(LEFT($A26,1))*VALUE(LEFT(D$25,1))>=$C$14,"Moyen","Faible"))
A27: 2 Modérée | B27: =VALUE(LEFT($A27,1))*VALUE(LEFT(B$25,1))&" : "&IF(VALUE(LEFT($A27,1))*VALUE(LEFT(B$25,1))>=$C$15,"Élevé",IF(VALUE(LEFT($A27,1))*VALUE(LEFT(B$25,1))>=$C$14,"Moyen","Faible")) | C27: =VALUE(LEFT($A27,1))*VALUE(LEFT(C$25,1))&" : "&IF(VALUE(LEFT($A27,1))*VALUE(LEFT(C$25,1))>=$C$15,"Élevé",IF(VALUE(LEFT($A27,1))*VALUE(LEFT(C$25,1))>=$C$14,"Moyen","Faible")) | D27: =VALUE(LEFT($A27,1))*VALUE(LEFT(D$25,1))&" : "&IF(VALUE(LEFT($A27,1))*VALUE(LEFT(D$25,1))>=$C$15,"Élevé",IF(VALUE(LEFT($A27,1))*VALUE(LEFT(D$25,1))>=$C$14,"Moyen","Faible"))
A28: 1 Légère | B28: =VALUE(LEFT($A28,1))*VALUE(LEFT(B$25,1))&" : "&IF(VALUE(LEFT($A28,1))*VALUE(LEFT(B$25,1))>=$C$15,"Élevé",IF(VALUE(LEFT($A28,1))*VALUE(LEFT(B$25,1))>=$C$14,"Moyen","Faible")) | C28: =VALUE(LEFT($A28,1))*VALUE(LEFT(C$25,1))&" : "&IF(VALUE(LEFT($A28,1))*VALUE(LEFT(C$25,1))>=$C$15,"Élevé",IF(VALUE(LEFT($A28,1))*VALUE(LEFT(C$25,1))>=$C$14,"Moyen","Faible")) | D28: =VALUE(LEFT($A28,1))*VALUE(LEFT(D$25,1))&" : "&IF(VALUE(LEFT($A28,1))*VALUE(LEFT(D$25,1))>=$C$15,"Élevé",IF(VALUE(LEFT($A28,1))*VALUE(LEFT(D$25,1))>=$C$14,"Moyen","Faible"))

Sheet Analyse de risques
A1: Analyse de risques de votre projet (ISO 14971 simplifiée)
A2: Équipe (numéro) | C2: eq05
A3: Cas d'usage | C3: A (chute)
A4: Finalité en une phrase | C4: Surveille en continu les constantes vitales et les mouvements des résidents, détecte les chutes et les malaises, prédit le risque et alerte le personnel soignant en moins d'une minute.
A7: 1. LA CHAÎNE DU RISQUE (dominos) | G7: 2. COTATION AVANT MESURES | K7: 3. MESURES, DANS L'ORDRE IMPOSÉ | N7: 4. RISQUE RÉSIDUEL | R7: 5. JUSTIFIER
A8: N° | B8: Type de danger | C8: Danger | D8: Séquence d'événements | E8: Situation dangereuse | F8: Dommage | G8: Gravité (1-3) | H8: Probabilité (1-3) | I8: Risque = G × P | J8: Niveau | K8: Mesure 1 — sécurité par la conception | L8: Mesure 2 — protection (alarme, garde-fou) | M8: Mesure 3 — information (notice, formation) | N8: Gravité après | O8: Probabilité après | P8: Risque résiduel | Q8: Niveau résiduel | R8: Lien module 2, bénéfice / risque, commentaire
A9: 1 | B9: Technique | C9: Batterie vide : le capteur ne peut plus envoyer d'alerte | D9: Recharge oubliée → batterie vide, capteur éteint la nuit → la résidente se lève et chute | E9: La résidente est au sol, personne n'est prévenu | F9: Longue attente au sol (plusieurs heures) : froid, déshydratation, escarres, hospitalisation | G9: 3 | H9: 3 | I9: =IF(OR(G9="",H9=""),"",G9*H9) | J9: =IF(I9="","",IF(I9>='Échelles'!$C$15,"Élevé : inacceptable",IF(I9>='Échelles'!$C$14,"Moyen : à réduire","Faible : acceptable"))) | K9: Batterie qui tient largement : au moins 7 jours (TP M2-4), mode sommeil entre deux mesures | L9: Alerte « batterie faible » au poste de soins ; alerte si l'objet se tait (pas de signe de vie depuis 1 h) | M9: Notice : « recharger chaque semaine » ; recharge inscrite au protocole de soins (ex. à la toilette) ; formation | N9: 3 | O9: 1 | P9: =IF(OR(N9="",O9=""),"",N9*O9) | Q9: =IF(P9="","",IF(P9>='Échelles'!$C$15,"Élevé : inacceptable",IF(P9>='Échelles'!$C$14,"Moyen : à réduire","Faible : acceptable"))) | R9: Lien M2 : l'autonomie de 7 jours est un OBJECTIF de conception : le TP M2-4 n'est pas dans le dépôt, le chiffre n'est donc pas encore mesuré (à mesurer au projet 1 ; si l'autonomie réelle est plus courte, la probabilité résiduelle remonte). Grave reste grave : au mieux « moyen ». Bénéfice : les chutes de nuit sont signalées en minutes, pas découvertes à la ronde.
A10: 2 | B10: Technique | C10: Chute non détectée : l'algorithme rate une chute lente | D10: Glissade lente le long du lit ou du fauteuil → l'accélération reste sous le seuil de détection → aucune alerte n'est émise → personne ne passe avant la ronde de nuit | E10: La résidente est au sol, le système croit la situation normale | F10: Attente prolongée au sol : hypothermie, déshydratation, rhabdomyolyse, hospitalisation | G10: 3 | H10: 2 | I10: =IF(OR(G10="",H10=""),"",G10*H10) | J10: =IF(I10="","",IF(I10>='Échelles'!$C$15,"Élevé : inacceptable",IF(I10>='Échelles'!$C$14,"Moyen : à réduire","Faible : acceptable"))) | K10: Règle à trois temps du TP M2-2 réglée pour privilégier le rappel, complétée par une détection d'immobilité prolongée au sol ; ajout d'une détection indépendante du bracelet : capteur de présence au sol dans la chambre (radar ou tapis), actif la nuit (fusion de sources : une chute ratée par le bracelet peut être vue par la chambre) | L10: Alerte « immobilité anormale » si aucun mouvement depuis 20 min hors plage de sommeil ; escalade automatique au poste de soins si l'alerte n'est pas prise | M10: Notice : le système ne remplace pas les rondes ; formation du personnel aux limites de la détection (chute lente, glissade) | N10: 3 | O10: 1 | P10: =IF(OR(N10="",O10=""),"",N10*O10) | Q10: =IF(P10="","",IF(P10>='Échelles'!$C$15,"Élevé : inacceptable",IF(P10>='Échelles'!$C$14,"Moyen : à réduire","Faible : acceptable"))) | R10: Lien M2 : la règle à trois temps n'a été testée que sur le jeu de secours SYNTHÉTIQUE (chutes de téléphone) ; la conclusion du TP M2-2 dit elle-même qu'elle rate le profil d'une chute humaine. Le bracelet seul ne justifie donc PAS « rare » : c'est le capteur de chambre indépendant qui fait descendre la probabilité. Cotation « rare » conditionnée à une validation sur des chutes humaines au projet 1 ; sans elle, le risque reste à 3 × 2 = 6 (élevé) et le système ne peut pas remplacer les rondes. Bénéfice : une chute signalée en minutes au lieu d'être découverte à la ronde suivante.
A11: 3 | B11: Technique | C11: Fausse alerte répétée : le système crie au loup | D11: Mouvement brusque (assis-debout, s'allonger) pris pour une chute → alertes répétées → le personnel perd confiance et acquitte sans se déplacer → une vraie alerte est acquittée comme une fausse | E11: Une alerte réelle est ignorée alors que la résidente est au sol | F11: Prise en charge retardée d'une chute réelle : attente au sol, aggravation, hospitalisation | G11: 3 | H11: 2 | I11: =IF(OR(G11="",H11=""),"",G11*H11) | J11: =IF(I11="","",IF(I11>='Échelles'!$C$15,"Élevé : inacceptable",IF(I11>='Échelles'!$C$14,"Moyen : à réduire","Faible : acceptable"))) | K11: Règle à trois temps au lieu du seuil naïf « > 2,5 g » (TP M2-2 : précision 0,75 → 1,00) ; confirmation par l'immobilité après l'impact avant toute émission d'alerte | L11: Alerte graduée à 5 niveaux : les niveaux bas s'affichent sans sonner ; l'acquittement demande un motif ; compteur de fausses alertes par résident suivi au tableau de bord | M11: Notice et formation : ne jamais acquitter une alerte sans avoir vu la personne ; revue mensuelle des seuils avec l'équipe soignante | N11: 3 | O11: 1 | P11: =IF(OR(N11="",O11=""),"",N11*O11) | Q11: =IF(P11="","",IF(P11>='Échelles'!$C$15,"Élevé : inacceptable",IF(P11>='Échelles'!$C$14,"Moyen : à réduire","Faible : acceptable"))) | R11: Lien M2 : règle naïve > 2,5 g (précision 0,75) contre règle à trois temps (1,00). Mesure à double tranchant : durcir le seuil pour réduire les fausses alertes fait remonter le risque n° 2. Bénéfice : des alertes rares et crédibles sont des alertes suivies.
A12: 4 | B12: Utilisation | C12: Capteur mal porté, mal serré ou retiré | D12: Bracelet retiré pour la toilette ou la douche et non remis → signal PPG inexploitable ou absent → le résident est cru surveillé alors qu'il ne l'est plus | E12: Résident non surveillé sans que personne ne le sache | F12: Malaise ou chute non détecté : attente au sol, retard de soins, hospitalisation | G12: 3 | H12: 3 | I12: =IF(OR(G12="",H12=""),"",G12*H12) | J12: =IF(I12="","",IF(I12>='Échelles'!$C$15,"Élevé : inacceptable",IF(I12>='Échelles'!$C$14,"Moyen : à réduire","Faible : acceptable"))) | K12: Détection de port (contact peau) et règle qualité du TP M2-1 : une mesure douteuse n'est jamais publiée comme valeur valide, elle est publiée « indisponible » | L12: Bandeau « capteur non porté » sur la fiche du résident ; alerte au poste de soins si l'état « indisponible » dure plus de 30 min | M12: Notice : remettre le bracelet après la toilette ; pictogramme sur le socle de charge ; point ajouté au protocole de soins | N12: 3 | O12: 1 | P12: =IF(OR(N12="",O12=""),"",N12*O12) | Q12: =IF(P12="","",IF(P12>='Échelles'!$C$15,"Élevé : inacceptable",IF(P12>='Échelles'!$C$14,"Moyen : à réduire","Faible : acceptable"))) | R12: Lien M2 : règle qualité « mesure indisponible, jamais une fausse valeur » (TP M2-1). Grave reste grave : au mieux « moyen ». Bénéfice : l'absence de surveillance devient visible au lieu d'être silencieuse.
A13: 5 | B13: Utilisation | C13: Bracelets échangés : les constantes sont attribuées au mauvais résident | D13: Deux bracelets échangés au retour de charge → les constantes de M. X s'affichent sous le nom de Mme Y → l'alerte part vers la mauvaise chambre | E13: Les soignants cherchent dans la mauvaise chambre pendant que l'autre résident est au sol | F13: Retard de prise en charge de plusieurs minutes ; décision de soin fondée sur les constantes d'un autre résident | G13: 2 | H13: 2 | I13: =IF(OR(G13="",H13=""),"",G13*H13) | J13: =IF(I13="","",IF(I13>='Échelles'!$C$15,"Élevé : inacceptable",IF(I13>='Échelles'!$C$14,"Moyen : à réduire","Faible : acceptable"))) | K13: Un identifiant unique et un certificat par objet (addendum sécurité M2) ; association résident ↔ bracelet verrouillée côté backend, jamais sur le socle de charge | L13: Contrôle de cohérence : alerte si le profil physiologique d'un résident change brutalement ; numéro de l'objet affiché à côté du nom sur le tableau de bord | M13: Notice : vérifier l'identifiant au dos du bracelet à chaque remise ; procédure de ré-appairage écrite et affichée | N13: 2 | O13: 1 | P13: =IF(OR(N13="",O13=""),"",N13*O13) | Q13: =IF(P13="","",IF(P13>='Échelles'!$C$15,"Élevé : inacceptable",IF(P13>='Échelles'!$C$14,"Moyen : à réduire","Faible : acceptable"))) | R13: Bénéfice : l'erreur d'identité devient détectable au lieu de passer inaperçue. Risque résiduel faible, accepté et noté.
A14: 6 | B14: Cybersécurité | C14: Données de santé interceptées sur le réseau (atteinte à la vie privée) | D14: MQTT publié en clair (port 1883, sans TLS : état actuel du dépôt) et Bluetooth non appairé → un tiers présent sur le réseau de l'établissement écoute le trafic → constantes, déplacements et horaires des résidents captés | E14: Les données de santé d'un résident identifiable circulent en clair dans l'établissement | F14: Atteinte à la vie privée (donnée de santé, RGPD art. 9), repérage des absences ; pas d'atteinte physique directe ni de soins nécessaires | G14: 1 | H14: 2 | I14: =IF(OR(G14="",H14=""),"",G14*H14) | J14: =IF(I14="","",IF(I14>='Échelles'!$C$15,"Élevé : inacceptable",IF(I14>='Échelles'!$C$14,"Moyen : à réduire","Faible : acceptable"))) | K14: MQTT chiffré TLS sur le port 8883, un certificat par objet, Bluetooth appairé et chiffré, comptes séparés par service (addendum sécurité M2) ; aucune donnée nominative dans les topics | L14: Rejet et journalisation des connexions non authentifiées ; alerte sur connexion inconnue au broker ; rotation des certificats | M14: Notice d'installation : ne jamais exposer le broker sur Internet ; procédure de mise en service ; sensibilisation RGPD du personnel | N14: 1 | O14: 1 | P14: =IF(OR(N14="",O14=""),"",N14*O14) | Q14: =IF(P14="","",IF(P14>='Échelles'!$C$15,"Élevé : inacceptable",IF(P14>='Échelles'!$C$14,"Moyen : à réduire","Faible : acceptable"))) | R14: Gravité cotée 1 : l'échelle du cours mesure l'atteinte à la SANTÉ (« Modérée » = soins nécessaires, ce qui n'est pas le cas ici). Ce score faible ne veut pas dire que le risque est négligeable : il relève aussi du RGPD (AIPD) et de l'IEC 81001-5-1 / MDCG 2019-16, traités hors de cette matrice. MESURES À METTRE EN ŒUVRE : le dépôt est aujourd'hui en 1883 sans TLS avec allow_anonymous true (docs/contrat_mqtt.md) ; la cotation résiduelle ne vaut qu'une fois TLS 8883 et les certificats en place. Fait vérifié dans le dépôt : le pont Mosquitto relaie vitals/resident/+, motion/resident/+ et alerts/new vers broker.hivemq.com, broker PUBLIC en 1883 anonyme (mosquitto/config/mosquitto.conf). Données fictives aujourd'hui ; ce pont doit disparaître avant toute donnée réelle, et il est à décrire tel quel dans l'AIPD.
A15: 7 | B15: Technique | C15: Surveillance interrompue : broker saturé ou réseau coupé | D15: Saturation du broker ou panne Wi-Fi → plus aucun message ne remonte → le tableau de bord continue d'afficher les dernières valeurs connues → les soignants croient la surveillance active | E15: Surveillance interrompue sans que personne ne le voie ; une chute survient pendant la coupure | F15: Chute non signalée pendant la panne : attente prolongée au sol, hospitalisation | G15: 3 | H15: 2 | I15: =IF(OR(G15="",H15=""),"",G15*H15) | J15: =IF(I15="","",IF(I15>='Échelles'!$C$15,"Élevé : inacceptable",IF(I15>='Échelles'!$C$14,"Moyen : à réduire","Faible : acceptable"))) | K15: Signe de vie périodique par objet et horodatage de chaque mesure ; file locale sur la passerelle qui rejoue les messages après la coupure ; broker redondé | L15: Bandeau rouge « système dégradé » au poste de soins dès 5 min sans signe de vie, avec bascule explicite en rondes renforcées | M15: Procédure dégradée écrite (qui appeler, à quelle fréquence passer) et jouée en formation | N15: 3 | O15: 1 | P15: =IF(OR(N15="",O15=""),"",N15*O15) | Q15: =IF(P15="","",IF(P15>='Échelles'!$C$15,"Élevé : inacceptable",IF(P15>='Échelles'!$C$14,"Moyen : à réduire","Faible : acceptable"))) | R15: Reclassé en « Technique » : une panne ou une saturation n'est pas une attaque (l'attaque volontaire est traitée ligne 9). Aucune donnée périmée affichée comme fraîche : c'est la règle « mesure indisponible » du M2 appliquée au transport. Gravité irréductible ; bénéfice : la panne devient visible en minutes au lieu d'être découverte après coup. À distinguer de l'AIPD : ici le dommage est l'absence de secours, pas la fuite de données.
A16: 8 | B16: Technique | C16: Le modèle d'IA se trompe sur un profil de résident absent des données d'entraînement | D16: Résident en fauteuil ou à la démarche atypique → le modèle n'a jamais vu ce profil → score de risque faussement rassurant → ni alerte, ni surveillance renforcée | E16: Un résident à haut risque est considéré comme à risque faible | F16: Malaise ou chute ni anticipé ni détecté : retard de prise en charge, aggravation | G16: 3 | H16: 2 | I16: =IF(OR(G16="",H16=""),"",G16*H16) | J16: =IF(I16="","",IF(I16>='Échelles'!$C$15,"Élevé : inacceptable",IF(I16>='Échelles'!$C$14,"Moyen : à réduire","Faible : acceptable"))) | K16: Modèle hybride : la détection par règles (seuils physiologiques, règle à trois temps) reste active indépendamment du score IA, qui n'est jamais seul décisionnaire ; jeu d'entraînement couvrant les profils atypiques | L16: Score affiché avec son niveau de confiance ; alerte « profil hors domaine » qui bascule explicitement sur les règles ; revue mensuelle des faux négatifs | M16: Notice : le score de risque est une aide, pas un diagnostic ; formation du personnel à ses limites | N16: 3 | O16: 1 | P16: =IF(OR(N16="",O16=""),"",N16*O16) | Q16: =IF(P16="","",IF(P16>='Échelles'!$C$15,"Élevé : inacceptable",IF(P16>='Échelles'!$C$14,"Moyen : à réduire","Faible : acceptable"))) | R16: Si le projet est classé IIa ou plus (voir TP M3-1), une détection de chute par IA est une IA « à haut risque » au sens de l'AI Act, avec des obligations au 2 août 2028. Gravité irréductible ; bénéfice : le score priorise les rondes sans jamais désactiver les règles.
A17: 9 | B17: Cybersécurité | C17: Fausses données injectées : un client non autorisé publie sur le broker | D17: Broker accessible sans authentification (allow_anonymous true, port 1883 : état actuel du dépôt) → un client non autorisé publie de fausses constantes « normales », ou brouille / sature le canal, sur les topics d'un résident → la vraie chute est masquée ou noyée | E17: La résidente est au sol, le tableau de bord affiche des constantes normales | F17: Chute ou malaise non pris en charge : attente prolongée au sol, aggravation, hospitalisation | G17: 3 | H17: 2 | I17: =IF(OR(G17="",H17=""),"",G17*H17) | J17: =IF(I17="","",IF(I17>='Échelles'!$C$15,"Élevé : inacceptable",IF(I17>='Échelles'!$C$14,"Moyen : à réduire","Faible : acceptable"))) | K17: Authentification mutuelle TLS sur le port 8883 avec un certificat par objet (addendum sécurité M2) ; allow_anonymous false ; ACL par topic : chaque objet ne publie que sur son propre topic, seul le backend publie les alertes ; numéro de séquence et horodatage dans chaque message (anti-rejeu) | L17: Alerte sécurité au poste de soins sur connexion refusée, saut de séquence ou deux sources pour un même capteur ; journalisation des connexions ; bascule en « système dégradé » (comme ligne 7) si l'intégrité est douteuse | M17: Procédure de gestion des certificats (émission, révocation d'un bracelet perdu) ; plan de réponse à incident ; formation du personnel : signaler toute alerte ou valeur incohérente | N17: 3 | O17: 1 | P17: =IF(OR(N17="",O17=""),"",N17*O17) | Q17: =IF(P17="","",IF(P17>='Échelles'!$C$15,"Élevé : inacceptable",IF(P17>='Échelles'!$C$14,"Moyen : à réduire","Faible : acceptable"))) | R17: Lien M2 : addendum sécurité (TLS 8883, certificat par objet, comptes séparés). Cadre : IEC 81001-5-1, MDCG 2019-16. C'est le vrai danger cyber pour le PATIENT : une attaque qui masque une chute est un risque de santé, pas seulement de données. MESURES À METTRE EN ŒUVRE : tant que le broker reste anonyme en 1883, le risque reste à 3 × 2 = 6 (élevé). Gravité irréductible ; bénéfice : seules les données authentifiées peuvent déclencher ou masquer une alerte.
A18: 10 | B18: Technique | C18: Exemple de matériovigilance (hors projet) : canule du pod Omnipod qui peut se déchirer (rappel de lots ANSM, 3 juin 2026) | D18: Canule déchirée sous la peau → moins d'insuline délivrée que la dose programmée → le patient ne s'en rend pas compte | E18: Patient diabétique sous-dosé en insuline sans le savoir | F18: Hyperglycémie, pouvant aller jusqu'à l'acidocétose et l'hospitalisation | G18: 3 | H18: 2 | I18: =IF(OR(G18="",H18=""),"",G18*H18) | J18: =IF(I18="","",IF(I18>='Échelles'!$C$15,"Élevé : inacceptable",IF(I18>='Échelles'!$C$14,"Moyen : à réduire","Faible : acceptable"))) | K18: Correction du procédé de fabrication de la canule ; contrôle renforcé des lots | L18: Rappel des lots concernés ; alerte d'occlusion ou de délivrance anormale ; surveillance glycémique (capteur de glucose) qui signale la dérive | M18: Information de sécurité aux patients et aux soignants ; consigne : surveiller la glycémie et changer le pod en cas de valeurs hautes inexpliquées | N18: 3 | O18: 1 | P18: =IF(OR(N18="",O18=""),"",N18*O18) | Q18: =IF(P18="","",IF(P18>='Échelles'!$C$15,"Élevé : inacceptable",IF(P18>='Échelles'!$C$14,"Moyen : à réduire","Faible : acceptable"))) | R18: Exemple « pour aller plus loin », hors périmètre de notre projet : à retirer à l'analyse de risques v1 (projet 1). Il montre que l'analyse de risques continue après la vente : un incident remonté (matériovigilance) rouvre le dossier.
A19: Ligne 1 = exemple rempli (police bleue en italique) : gardez-le s'il vaut pour votre projet, ou remplacez-le.

Sheet Synthèse
A1: Synthèse : où sont vos risques ? (calculée automatiquement)
A3: AVANT les mesures | E3: APRÈS les mesures (risque résiduel)
A4: Gravité ↓ / Probabilité → | B4: 1 Rare | C4: 2 Possible | D4: 3 Fréquente | E4: Gravité ↓ / Probabilité → | F4: 1 Rare | G4: 2 Possible | H4: 3 Fréquente
A5: 3 Grave | B5: =COUNTIFS('Analyse de risques'!$G$9:$G$18,3,'Analyse de risques'!$H$9:$H$18,1) | C5: =COUNTIFS('Analyse de risques'!$G$9:$G$18,3,'Analyse de risques'!$H$9:$H$18,2) | D5: =COUNTIFS('Analyse de risques'!$G$9:$G$18,3,'Analyse de risques'!$H$9:$H$18,3) | E5: 3 Grave | F5: =COUNTIFS('Analyse de risques'!$N$9:$N$18,3,'Analyse de risques'!$O$9:$O$18,1) | G5: =COUNTIFS('Analyse de risques'!$N$9:$N$18,3,'Analyse de risques'!$O$9:$O$18,2) | H5: =COUNTIFS('Analyse de risques'!$N$9:$N$18,3,'Analyse de risques'!$O$9:$O$18,3)
A6: 2 Modérée | B6: =COUNTIFS('Analyse de risques'!$G$9:$G$18,2,'Analyse de risques'!$H$9:$H$18,1) | C6: =COUNTIFS('Analyse de risques'!$G$9:$G$18,2,'Analyse de risques'!$H$9:$H$18,2) | D6: =COUNTIFS('Analyse de risques'!$G$9:$G$18,2,'Analyse de risques'!$H$9:$H$18,3) | E6: 2 Modérée | F6: =COUNTIFS('Analyse de risques'!$N$9:$N$18,2,'Analyse de risques'!$O$9:$O$18,1) | G6: =COUNTIFS('Analyse de risques'!$N$9:$N$18,2,'Analyse de risques'!$O$9:$O$18,2) | H6: =COUNTIFS('Analyse de risques'!$N$9:$N$18,2,'Analyse de risques'!$O$9:$O$18,3)
A7: 1 Légère | B7: =COUNTIFS('Analyse de risques'!$G$9:$G$18,1,'Analyse de risques'!$H$9:$H$18,1) | C7: =COUNTIFS('Analyse de risques'!$G$9:$G$18,1,'Analyse de risques'!$H$9:$H$18,2) | D7: =COUNTIFS('Analyse de risques'!$G$9:$G$18,1,'Analyse de risques'!$H$9:$H$18,3) | E7: 1 Légère | F7: =COUNTIFS('Analyse de risques'!$N$9:$N$18,1,'Analyse de risques'!$O$9:$O$18,1) | G7: =COUNTIFS('Analyse de risques'!$N$9:$N$18,1,'Analyse de risques'!$O$9:$O$18,2) | H7: =COUNTIFS('Analyse de risques'!$N$9:$N$18,1,'Analyse de risques'!$O$9:$O$18,3)
A8: (nombre de risques dans chaque case) | E8: (nombre de risques dans chaque case)
A11: Contrôles
A12: Dangers listés | B12: =COUNTA('Analyse de risques'!$C$9:$C$18) | C12: =IF(B12>=5,"OK : au moins 5 dangers","Visez au moins 5 dangers")
A13: dont techniques | B13: =COUNTIF('Analyse de risques'!$B$9:$B$18,"Technique") | C13: =IF(B13>=1,"OK","Ajoutez un danger technique")
A14: dont d'utilisation | B14: =COUNTIF('Analyse de risques'!$B$9:$B$18,"Utilisation") | C14: =IF(B14>=1,"OK","Ajoutez un danger d'utilisation")
A15: dont de cybersécurité | B15: =COUNTIF('Analyse de risques'!$B$9:$B$18,"Cybersécurité") | C15: =IF(B15>=1,"OK","Ajoutez un danger de cybersécurité")
A16: Risques « élevés » après mesures | B16: =COUNTIF('Analyse de risques'!$Q$9:$Q$18,"Élevé*") | C16: =IF(B16=0,"OK : aucun risque inacceptable restant","Il reste un risque inacceptable : ajoutez une mesure")
